{
  "display_name": "settlement.xuanhuan_earth.mountain_spirit_shrine",
  "category": "spirit_society",
  "generation_status": "catalog_only",
  "weight": 4,
  "min_distance_chunks": 32,
  "biomes": ["#minecraft:is_mountain", "#minecraft:is_taiga"],
  "buildings": ["mountain_gate", "incense_court", "spirit_stone_altar", "keeper_lodge"],
  "residents": ["shrine_keeper", "mountain_spirit_envoy", "pilgrim"],
  "outputs": ["xuanhuan_earth:spirit_crystal_shard", "xuanhuan_earth:spirit_spring_bottle"]
}
